golden_utils/__init__.py
golden_utils/goldenutils.py
golden_utils-0.1.3.dist-info/licenses/LICENSE
utilidades/__init__.py
utilidades/utilidades.py
golden_utils-0.1.3.dist-info/METADATA
golden_utils-0.1.3.dist-info/WHEEL
golden_utils-0.1.3.dist-info/top_level.txt
golden_utils-0.1.3.dist-info/RECORD
